README
osscmd
setup.py
oss/__init__.py
oss/oss_api.py
oss/oss_sample.py
oss/oss_util.py
oss/oss_xml_handler.py
oss/pkg_info.py
osssdk.egg-info/PKG-INFO
osssdk.egg-info/SOURCES.txt
osssdk.egg-info/dependency_links.txt
osssdk.egg-info/top_level.txt